hologridgen/__init__.py
hologridgen-1.0.1.dist-info/LICENSE
hologridgen-1.0.1.dist-info/METADATA
hologridgen-1.0.1.dist-info/WHEEL
hologridgen-1.0.1.dist-info/top_level.txt
hologridgen-1.0.1.dist-info/RECORD
