Metadata-Version: 2.1
Name: hologridgen
Version: 1.0.1
Summary: UNKNOWN
Home-page: https://github.com/pygridgen/hologridgen
Author: jlstevens
Author-email: jstevens@anaconda.com
License: CC0
Project-URL: Bug Tracker, https://github.com/pygridgen/hologridgen/issues
Project-URL: Source Code, https://github.com/pygridgen/hologridgen
Platform: Windows
Platform: Mac OS X
Platform: Linux
Classifier: License :: CC0 1.0 Universal (CC0 1.0) Public Domain Dedication
Classifier: Development Status :: 5 - Production/Stable
Classifier: Programming Language :: Python :: 3.5
Classifier: Programming Language :: Python :: 3.6
Classifier: Programming Language :: Python :: 3.7
Classifier: Programming Language :: Python :: 3.8
Classifier: Operating System :: OS Independent
Classifier: Intended Audience :: Science/Research
Classifier: Intended Audience :: Developers
Classifier: Natural Language :: English
Classifier: Topic :: Scientific/Engineering
Classifier: Topic :: Software Development :: Libraries
Provides: hologridgen
Requires-Python: >=3.5
Requires-Dist: param (>=1.10.0)
Requires-Dist: panel (>=0.10.0)
Requires-Dist: pygridgen (>0.2)
Requires-Dist: geopandas (>=0.8.1)
Requires-Dist: holoviews (>=1.13.5)
